aroundme/__init__.py
aroundme/__main__.py
aroundme-1.0.dist-info/LICENSE
aroundme-1.0.dist-info/METADATA
aroundme-1.0.dist-info/WHEEL
aroundme-1.0.dist-info/entry_points.txt
aroundme-1.0.dist-info/top_level.txt
aroundme-1.0.dist-info/RECORD
