Metadata-Version: 2.1
Name: aroundme
Version: 1.0
Summary: Find interesting places around you.
Home-page: https://github.com/rishabh570/what-is-around
Author: Rishabh Rawat
Author-email: icode365@gmail.com
License: MIT
Platform: UNKNOWN
Requires-Dist: googlemaps
